README.md
setup.cfg
setup.py
prometheus_file_content_exporter/__init__.py
prometheus_file_content_exporter/config.py
prometheus_file_content_exporter/main.py
prometheus_file_content_exporter.egg-info/PKG-INFO
prometheus_file_content_exporter.egg-info/SOURCES.txt
prometheus_file_content_exporter.egg-info/dependency_links.txt
prometheus_file_content_exporter.egg-info/entry_points.txt
prometheus_file_content_exporter.egg-info/requires.txt
prometheus_file_content_exporter.egg-info/top_level.txt