Metadata-Version: 1.2
Name: prometheus-file-content-exporter
Version: 0.2.1
Summary: Prometheus file content exporter
Home-page: https://github.com/spreaker/prometheus-file-content-exporter
Author: Marcin Brański
Author-email: marcin.branski@spreaker.com
License: UNKNOWN
Keywords: prometheus,exporter
Platform: UNKNOWN
Requires-Python:  >= 3
